MANIFEST.in
UNLICENSE
VERSION
distribute_setup.py
setup.py
lib/zmqc.py
lib/zmqc.egg-info/PKG-INFO
lib/zmqc.egg-info/SOURCES.txt
lib/zmqc.egg-info/dependency_links.txt
lib/zmqc.egg-info/entry_points.txt
lib/zmqc.egg-info/requires.txt
lib/zmqc.egg-info/top_level.txt