Metadata-Version: 1.0
Name: zmqc
Version: 0.1.0
Summary: A small but powerful command-line interface to ØMQ.
Home-page: http://github.com/zacharyvoase/zmqc
Author: Zachary Voase
Author-email: z@zacharyvoase.com
License: UNKNOWN
Platform: UNKNOWN
